trulia_rapidapi/tests.py
trulia_rapidapi/src/trulia_api.py
trulia_rapidapi/src/trulia_models/base.py
trulia_rapidapi/src/trulia_models/details_model.py
trulia_rapidapi/src/trulia_models/enums.py
trulia_rapidapi/src/trulia_models/listing_model.py
trulia_rapidapi/src/trulia_models/search_token_model.py
trulia_rapidapi-0.1.4.dist-info/METADATA
trulia_rapidapi-0.1.4.dist-info/WHEEL
trulia_rapidapi-0.1.4.dist-info/top_level.txt
trulia_rapidapi-0.1.4.dist-info/RECORD
