Metadata-Version: 2.1
Name: trulia_rapidapi
Version: 0.1.4
Summary: Trulia Real Estate API on RapidAPI
Home-page: https://letsscrape.com/scrapers/trulia-real-estate-api/
Author: LetsScrape
Author-email: hello@letsscrape.com
Project-URL: Documentation, https://rapidapi.com/letsscrape/api/trulia-real-estate-scraper/
Project-URL: Bug Reports, https://github.com/letsscrape/python_trulia_rapidapi/issues
Project-URL: Source Code, https://github.com/letsscrape/python_trulia_rapidapi
Keywords: trulia,real estate api,trulia real estate,trulia api,parsing,scraper
